qmsolve/__init__.py
qmsolve/eigenstates.py
qmsolve/hamiltonian.py
qmsolve/particle_system/__init__.py
qmsolve/particle_system/particle_system.py
qmsolve/particle_system/single_particle.py
qmsolve/particle_system/two_bosons.py
qmsolve/particle_system/two_distinguishable_particles.py
qmsolve/particle_system/two_fermions.py
qmsolve/particle_system/two_particles.py
qmsolve/time_dependent_solver/__init__.py
qmsolve/time_dependent_solver/crank_nicolson.py
qmsolve/time_dependent_solver/method.py
qmsolve/time_dependent_solver/split_step.py
qmsolve/time_dependent_solver/time_dependent_solver.py
qmsolve/util/__init__.py
qmsolve/util/colour_functions.py
qmsolve/util/constants.py
qmsolve/util/file_handling.py
qmsolve/visualization/__init__.py
qmsolve/visualization/complex_slider_widget.py
qmsolve/visualization/single_particle_1D.py
qmsolve/visualization/single_particle_2D.py
qmsolve/visualization/single_particle_3D.py
qmsolve/visualization/two_identical_particles_1D.py
qmsolve/visualization/visualization.py
qmsolve-2.0.0.dist-info/LICENSE
qmsolve-2.0.0.dist-info/METADATA
qmsolve-2.0.0.dist-info/WHEEL
qmsolve-2.0.0.dist-info/top_level.txt
qmsolve-2.0.0.dist-info/RECORD
