Metadata-Version: 2.1
Name: qmsolve
Version: 2.0.0
Summary: A module for solving and visualizing the Schrödinger equation
Home-page: https://github.com/quantum-visualizations/qmsolve
Author: Rafael de la Fuente, marl0ny, Hudson Smith
Author-email: rafael.fuente.herrezuelo@gmail.com, lammarlonaurel123456789@gmail.com, dhudsmith@gmail.com
License: BSD-3-Clause
Download-URL: https://github.com/quantum-visualizations/qmsolve/archive/main.zip
Keywords: schrödinger-equation,quantum-physics,quantum-mechanics,quantum-programming
Platform: UNKNOWN
Classifier: Development Status :: 5 - Production/Stable
Classifier: Intended Audience :: Science/Research
Classifier: Topic :: Scientific/Engineering
Classifier: License :: OSI Approved :: BSD License
Classifier: Operating System :: OS Independent
Requires-Python: >=3.7
Requires-Dist: numpy
Requires-Dist: scipy
Requires-Dist: matplotlib
Requires-Dist: h5py
Requires-Dist: progressbar
Provides-Extra: with_mayavi
Requires-Dist: vtk (==8.1.2) ; (python_version=="3.7") and extra == 'with_mayavi'
Requires-Dist: mayavi (>=4.7.1) ; (python_version=="3.7") and extra == 'with_mayavi'
Requires-Dist: PyQt5 (>=5.14.1) ; (python_version=="3.7") and extra == 'with_mayavi'
Requires-Dist: vtk (==9.0.1) ; (python_version>="3.8") and extra == 'with_mayavi'
Requires-Dist: mayavi (>=4.7.1) ; (python_version>="3.8") and extra == 'with_mayavi'
Requires-Dist: PyQt5 (>=5.14.1) ; (python_version>="3.8") and extra == 'with_mayavi'
